{
  "kublai": {
    "agent": "kublai",
    "vote": "APPROVE",
    "timestamp": "2026-03-11T15:42:40.054094",
    "reason": null
  },
  "temujin": {
    "agent": "temujin",
    "vote": "APPROVE",
    "timestamp": "2026-03-11T15:42:40.085839",
    "reason": null
  },
  "mongke": {
    "agent": "mongke",
    "vote": "APPROVE",
    "timestamp": "2026-03-11T15:42:40.116358",
    "reason": null
  },
  "chagatai": {
    "agent": "chagatai",
    "vote": "APPROVE",
    "timestamp": "2026-03-11T15:42:40.147335",
    "reason": null
  },
  "jochi": {
    "agent": "jochi",
    "vote": "APPROVE",
    "timestamp": "2026-03-11T15:42:40.177202",
    "reason": null
  },
  "ogedei": {
    "agent": "ogedei",
    "vote": "APPROVE",
    "timestamp": "2026-03-11T15:42:40.208003",
    "reason": null
  }
}